LICENSE
README.md
setup.py
haas_proxy/__init__.py
haas_proxy/__main__.py
haas_proxy/balancer.py
haas_proxy/constants.py
haas_proxy/log.py
haas_proxy/proxy.py
haas_proxy/utils.py
haas_proxy.egg-info/PKG-INFO
haas_proxy.egg-info/SOURCES.txt
haas_proxy.egg-info/dependency_links.txt
haas_proxy.egg-info/requires.txt
haas_proxy.egg-info/top_level.txt
haas_proxy/twisted/plugins/haas_proxy_plugin.py